cta.py
car_talk_archiver-1.0.5.dist-info/METADATA
car_talk_archiver-1.0.5.dist-info/WHEEL
car_talk_archiver-1.0.5.dist-info/licenses/LICENSE
car_talk_archiver-1.0.5.dist-info/RECORD
