Metadata-Version: 2.4
Name: car-talk-archiver
Version: 1.0.5
Summary: 
License: MIT
License-File: LICENSE
Author: Brett Heinkel
Author-email: bheinks@gmail.com
Requires-Python: >=3.13,<4.0
Classifier: License :: OSI Approved :: MIT License
Classifier: Programming Language :: Python :: 3
Classifier: Programming Language :: Python :: 3.13
Classifier: Programming Language :: Python :: 3.14
Requires-Dist: beautifulsoup4 (>=4.14.3,<5.0.0)
Requires-Dist: feedgen (>=1.0.0,<2.0.0)
Requires-Dist: lxml (>=6.0.2,<7.0.0)
Requires-Dist: requests (>=2.32.5,<3.0.0)
Project-URL: Homepage, https://github.com/bheinks/car-talk-archiver
